iltero/__init__.py
iltero/__main__.py
iltero/cli.py
iltero/version.py
iltero/api_client/.gitignore
iltero/api_client/README.md
iltero/api_client/__init__.py
iltero/api_client/client.py
iltero/api_client/errors.py
iltero/api_client/pyproject.toml
iltero/api_client/types.py
iltero/api_client/api/__init__.py
iltero/api_client/api/audit_trail/__init__.py
iltero/api_client/api/audit_trail/audittrail_get_resource_history_47d06253.py
iltero/api_client/api/audit_trail/audittrail_get_user_activity_79ee32e5.py
iltero/api_client/api/audit_trail/audittrail_search_audit_logs_f45b25e2.py
iltero/api_client/api/auth/__init__.py
iltero/api_client/api/auth/login.py
iltero/api_client/api/auth/login_get_session_2f9bcd1a.py
iltero/api_client/api/auth/login_logout_69ed9c37.py
iltero/api_client/api/compliance_manifests/__init__.py
iltero/api_client/api/compliance_manifests/generate_manifest.py
iltero/api_client/api/compliance_manifests/get_manifest_by_bundle.py
iltero/api_client/api/compliance_manifests/verify_manifest.py
iltero/api_client/api/compliance_policies/__init__.py
iltero/api_client/api/compliance_policies/create_policy.py
iltero/api_client/api/compliance_policies/create_policy_set.py
iltero/api_client/api/compliance_policies/delete_policy_set.py
iltero/api_client/api/compliance_policies/get_policy_set.py
iltero/api_client/api/compliance_policies/list_policies.py
iltero/api_client/api/compliance_policies/list_policy_sets.py
iltero/api_client/api/compliance_policies/policy_delete_policy_46da02b4.py
iltero/api_client/api/compliance_policies/policy_get_policy_965bc6dd.py
iltero/api_client/api/compliance_policies/policy_get_policy_violations_b215dff8.py
iltero/api_client/api/compliance_policies/policy_update_policy_50c97599.py
iltero/api_client/api/compliance_policies/update_policy_set.py
iltero/api_client/api/compliance_remediation/__init__.py
iltero/api_client/api/compliance_remediation/create_remediation.py
iltero/api_client/api/compliance_remediation/execute_remediation.py
iltero_cli-0.1.1.dist-info/METADATA
iltero_cli-0.1.1.dist-info/WHEEL
iltero_cli-0.1.1.dist-info/entry_points.txt
iltero_cli-0.1.1.dist-info/licenses/LICENSE
iltero_cli-0.1.1.dist-info/RECORD
