Metadata-Version: 2.4
Name: iltero-cli
Version: 0.1.1
Summary: Unified CLI for Iltero platform
Author: Iltero Team
License: Apache-2.0
License-File: LICENSE
Requires-Python: >=3.11
Requires-Dist: attrs>=25.4.0
Requires-Dist: click>=8.1.0
Requires-Dist: httpx>=0.27.0
Requires-Dist: jinja2>=3.1.0
Requires-Dist: keyring>=25.0.0
Requires-Dist: orjson>=3.10.0
Requires-Dist: packaging>=24.0
Requires-Dist: pydantic-settings>=2.4.0
Requires-Dist: pydantic>=2.8.0
Requires-Dist: python-dateutil>=2.9.0.post0
Requires-Dist: python-dotenv>=1.0.0
Requires-Dist: pyyaml>=6.0
Requires-Dist: rich>=13.7.0
Requires-Dist: typer[all]>=0.12.0
Provides-Extra: dev
Requires-Dist: black>=24.8.0; extra == 'dev'
Requires-Dist: mypy>=1.11.0; extra == 'dev'
Requires-Dist: openapi-python-client>=0.27.1; extra == 'dev'
Requires-Dist: pre-commit>=3.8.0; extra == 'dev'
Requires-Dist: pytest-asyncio>=0.23.0; extra == 'dev'
Requires-Dist: pytest-cov>=5.0.0; extra == 'dev'
Requires-Dist: pytest-mock>=3.14.0; extra == 'dev'
Requires-Dist: pytest>=8.3.0; extra == 'dev'
Requires-Dist: ruff>=0.5.0; extra == 'dev'
Provides-Extra: scanners
Requires-Dist: checkov>=3.2.0; extra == 'scanners'
Requires-Dist: requests>=2.32.0; extra == 'scanners'
